imitate/__init__.py
imitate/consumer/__init__.py
imitate/producer/__init__.py
imitate/producer/message_record.py
imitate/producer/produce_result.py
imitate/producer/producer.py
imitate_client_snapshot-2022.0.0.dist-info/METADATA
imitate_client_snapshot-2022.0.0.dist-info/WHEEL
imitate_client_snapshot-2022.0.0.dist-info/top_level.txt
imitate_client_snapshot-2022.0.0.dist-info/RECORD
