Metadata-Version: 2.1
Name: imitate-client-snapshot
Version: 2022.0.0
Summary: imitate-client for python.
Home-page: UNKNOWN
Author: joecqupt
Author-email: joe469391363@gmail.com
License: UNKNOWN
Keywords: mq,client
Platform: UNKNOWN
Requires-Python: >=3.6
Requires-Dist: setuptools (>=21.0.0)
